{
  "submitter" : "Reach",
  "model_relation" : "extension",
  "extracted_information" : {
    "interaction_type" : "transcribes",
    "negative_information" : false,
    "participant_b" : {
      "in_model" : true,
      "identifier" : "pfam:PF00047",
      "entity_text" : "Ig",
      "entity_type" : "family"
    },
    "hypothesis_information" : false,
    "context" : {
      "Species" : [ "taxonomy:9823" ],
      "TissueType" : [ "tissuelist:TS-0068" ],
      "CellType" : [ "cl:CL:0000236" ]
    }
  },
  "verbose_text" : "A pig lacking a functional HC locus should be devoid of Ig expression and B cells, and, therefore, completely deficient in Ab mediated humoral immune responses.",
  "reading_complete" : "2020-08-08T14:15:23Z",
  "reader_type" : "machine",
  "reading_started" : "2020-08-08T14:12:51Z",
  "trigger" : "expression",
  "evidence" : [ "Ig expression" ],
  "pmc_id" : "7089184",
  "score" : 0
}