{
  "submitter" : "Reach",
  "model_relation" : "extension",
  "extracted_information" : {
    "interaction_type" : "transcribes",
    "negative_information" : false,
    "participant_b" : {
      "in_model" : true,
      "identifier" : "uaz:UAZ01412",
      "entity_text" : "estrogen receptor-alpha",
      "entity_type" : "gene"
    },
    "hypothesis_information" : false,
    "context" : {
      "Species" : [ "taxonomy:9606" ],
      "Organ" : [ "uberon:UBERON:0003891" ]
    }
  },
  "verbose_text" : "A significant decrease was also observed in the stromal expression of estrogen receptor-alpha in the LNG group.",
  "reading_complete" : "2020-08-04T19:57:52Z",
  "reader_type" : "machine",
  "reading_started" : "2020-08-04T19:57:02Z",
  "trigger" : "expression",
  "evidence" : [ "expression of estrogen receptor-alpha" ],
  "pmc_id" : "2646790",
  "score" : 0
}