{
  "submitter" : "Reach",
  "model_relation" : "extension",
  "extracted_information" : {
    "interaction_type" : "transcribes",
    "negative_information" : false,
    "participant_b" : {
      "in_model" : true,
      "identifier" : "uaz:UAZ03974",
      "entity_text" : "ChR2-eYFP",
      "entity_type" : "gene"
    },
    "hypothesis_information" : false,
    "context" : {
      "Species" : [ "taxonomy:10090" ],
      "Organ" : [ "uberon:UBERON:0001393" ],
      "CellType" : [ "cl:CL:0000540" ]
    }
  },
  "verbose_text" : "We found expression of ChR2-eYFP in 91% of PV positive neurons (602/661 PV neurons, n = 6 mice) with a false positive rate for ChR2-eYFP expression in PV negative neurons of 1% (31/3943 non PV neurons, n = 6 mice, XREF_FIG).",
  "reading_complete" : "2020-08-08T15:47:54Z",
  "reader_type" : "machine",
  "reading_started" : "2020-08-08T15:44:07Z",
  "trigger" : "expression",
  "evidence" : [ "ChR2-eYFP expression" ],
  "pmc_id" : "7191518",
  "score" : 0
}