{
  "submitter" : "Reach",
  "model_relation" : "extension",
  "extracted_information" : {
    "interaction_type" : "transcribes",
    "negative_information" : false,
    "participant_b" : {
      "in_model" : true,
      "identifier" : "uaz:UAZ00874",
      "entity_text" : "SIRPalpha",
      "entity_type" : "gene"
    },
    "hypothesis_information" : false,
    "context" : {
      "TissueType" : [ "tissuelist:TS-0488" ],
      "Organ" : [ "uberon:UBERON:0000479" ],
      "CellType" : [ "cl:CL:0000990" ],
      "Species" : [ "taxonomy:9606" ]
    }
  },
  "verbose_text" : "DN cDCs seemed more heterogeneous with at least three other subsets based on SIRPalpha and CD26 expression (XREF_FIG).",
  "reading_complete" : "2020-08-04T10:08:42Z",
  "reader_type" : "machine",
  "reading_started" : "2020-08-04T10:03:47Z",
  "trigger" : "expression",
  "evidence" : [ "SIRPalpha and CD26 expression" ],
  "pmc_id" : "7093381",
  "score" : 0
}