{
  "submitter" : "Reach",
  "model_relation" : "extension",
  "extracted_information" : {
    "interaction_type" : "transcribes",
    "negative_information" : false,
    "participant_b" : {
      "in_model" : true,
      "identifier" : "uaz:UAZ02417",
      "entity_text" : "vgQE",
      "entity_type" : "gene"
    },
    "hypothesis_information" : false,
    "context" : {
      "Species" : [ "taxonomy:5270" ],
      "TissueType" : [ "tissuelist:TS-1122" ],
      "Organ" : [ "uberon:UBERON:0009856" ]
    }
  },
  "verbose_text" : "In addition, the vgQE, which is indirectly dependent on the activity of Hh and labels the wing pouch, is expressed.",
  "reading_complete" : "2020-08-04T11:06:36Z",
  "reader_type" : "machine",
  "reading_started" : "2020-08-04T11:04:53Z",
  "trigger" : "expressed",
  "evidence" : [ "vgQE, which is indirectly dependent on the activity of Hh and labels the wing pouch, is expressed" ],
  "pmc_id" : "6777356",
  "score" : 0
}