{
  "submitter" : "Reach",
  "model_relation" : "extension",
  "extracted_information" : {
    "interaction_type" : "Amount",
    "negative_information" : false,
    "participant_b" : {
      "in_model" : true,
      "identifier" : "pfam:PF04886",
      "entity_text" : "PT",
      "entity_type" : "family"
    },
    "hypothesis_information" : false,
    "context" : {
      "Species" : [ "taxonomy:9606" ],
      "TissueType" : [ "tissuelist:TS-0814" ],
      "Organ" : [ "uberon:UBERON:0000062" ]
    }
  },
  "verbose_text" : "Each historical concern may have slightly different clinical manifestations, for instance, a contamination that causes thromboembolism may manifest as portal vein thrombosis or thrombophlebitis, etc. Hence, the concerns were defined at appropriate higher levels of MedDRA, and calculations were performed at PT level.",
  "reading_complete" : "2020-08-05T21:29:49Z",
  "reader_type" : "machine",
  "reading_started" : "2020-08-05T21:28:59Z",
  "trigger" : "level",
  "evidence" : [ "PT level" ],
  "pmc_id" : "5765515",
  "score" : 0
}