{
  "submitter" : "Reach",
  "model_relation" : "extension",
  "extracted_information" : {
    "interaction_type" : "decreases_activity",
    "negative_information" : false,
    "participant_b" : {
      "in_model" : true,
      "identifier" : "pfam:PF07417",
      "entity_text" : "CRL",
      "entity_type" : "family"
    },
    "participant_a" : {
      "in_model" : true,
      "identifier" : "pfam:PF16374",
      "entity_text" : "Cif",
      "entity_type" : "family"
    },
    "hypothesis_information" : false
  },
  "verbose_text" : "By inhibiting CRL ubiquitin ligase activity, Cif causes the deregulation of a number of host cell functions.",
  "reading_complete" : "2020-08-04T11:27:49Z",
  "reader_type" : "machine",
  "reading_started" : "2020-08-04T11:26:38Z",
  "trigger" : "causes",
  "evidence" : [ "CRL ubiquitin ligase activity, Cif causes" ],
  "pmc_id" : "6078346",
  "score" : 0
}