{
  "submitter" : "Reach",
  "model_relation" : "extension",
  "extracted_information" : {
    "interaction_type" : "Amount",
    "negative_information" : false,
    "participant_b" : {
      "in_model" : true,
      "identifier" : "pfam:PF00047",
      "entity_text" : "Ig",
      "entity_type" : "family"
    },
    "hypothesis_information" : false,
    "context" : {
      "Species" : [ "taxonomy:9606" ],
      "TissueType" : [ "tissuelist:TS-0649" ],
      "CellType" : [ "cl:CL:0000786" ]
    }
  },
  "verbose_text" : "These cells often secrete large amounts of monoclonal Ig into the blood.",
  "reading_complete" : "2020-08-04T12:27:11Z",
  "reader_type" : "machine",
  "reading_started" : "2020-08-04T12:24:52Z",
  "trigger" : "amounts",
  "evidence" : [ "amounts of monoclonal Ig" ],
  "pmc_id" : "7105615",
  "score" : 0
}