{
  "submitter" : "Reach",
  "model_relation" : "extension",
  "extracted_information" : {
    "interaction_type" : "Amount",
    "negative_information" : false,
    "participant_b" : {
      "in_model" : true,
      "identifier" : "be:LDH",
      "entity_text" : "LDH",
      "entity_type" : "family"
    },
    "hypothesis_information" : false,
    "context" : {
      "CellLine" : [ "cellosaurus:CVCL_3694" ],
      "TissueType" : [ "tissuelist:TS-0079" ],
      "Species" : [ "taxonomy:9606" ]
    }
  },
  "verbose_text" : "She presented a severe grade of anemia (Hb 7.4 g/dL) requiring blood transfusion, piastrinopenia, a significantly high level of LDH (554 U/L), and leukocytosis with hypereosinophilia.",
  "reading_complete" : "2020-08-02T09:58:38Z",
  "reader_type" : "machine",
  "reading_started" : "2020-08-02T09:57:36Z",
  "trigger" : "level",
  "evidence" : [ "level of LDH" ],
  "pmc_id" : "6509925",
  "score" : 0
}