{
  "submitter" : "Reach",
  "model_relation" : "extension",
  "extracted_information" : {
    "interaction_type" : "Amount",
    "negative_information" : false,
    "participant_b" : {
      "in_model" : true,
      "identifier" : "pfam:PF00375",
      "entity_text" : "SDF",
      "entity_type" : "family"
    },
    "hypothesis_information" : false,
    "context" : {
      "TissueType" : [ "tissuelist:TS-0711" ],
      "Species" : [ "taxonomy:9606" ]
    }
  },
  "verbose_text" : "A certain level of SDF such as> 30% DFI by SCSA method should not be treated as an absolute value as it does not mean the remaining spermatozoa in a sample are normal.",
  "reading_complete" : "2020-08-04T12:25:13Z",
  "reader_type" : "machine",
  "reading_started" : "2020-08-04T12:24:56Z",
  "trigger" : "level",
  "evidence" : [ "level of SDF" ],
  "pmc_id" : "5643630",
  "score" : 0
}