{
  "submitter" : "Reach",
  "model_relation" : "extension",
  "extracted_information" : {
    "interaction_type" : "transcribes",
    "negative_information" : false,
    "participant_b" : {
      "in_model" : true,
      "identifier" : "uaz:UAZ04177",
      "entity_text" : "K V 4.3 channel",
      "entity_type" : "gene"
    },
    "hypothesis_information" : false,
    "context" : {
      "CellLine" : [ "cellosaurus:CVCL_0045" ],
      "Species" : [ "taxonomy:9606" ],
      "TissueType" : [ "tissuelist:TS-0439" ],
      "Organ" : [ "uberon:UBERON:0000104" ]
    }
  },
  "verbose_text" : "The expression of the K V 4.3 channel in normal or failing human and canine hearts exhibits a transmural gradient in the left ventricle, which is responsible for the transmural electrophysiological heterogeneity.",
  "reading_complete" : "2020-08-02T14:53:24Z",
  "reader_type" : "machine",
  "reading_started" : "2020-08-02T14:52:30Z",
  "trigger" : "expression",
  "evidence" : [ "expression of the K V 4.3 channel" ],
  "pmc_id" : "4494594",
  "score" : 0
}