{
  "submitter" : "Reach",
  "model_relation" : "extension",
  "extracted_information" : {
    "interaction_type" : "Amount",
    "negative_information" : false,
    "participant_b" : {
      "in_model" : true,
      "identifier" : "pfam:PF04159",
      "entity_text" : "NB",
      "entity_type" : "family"
    },
    "hypothesis_information" : false,
    "context" : {
      "Species" : [ "taxonomy:7227" ],
      "TissueType" : [ "tissuelist:TS-0679" ],
      "CellType" : [ "cl:CL:0000047" ]
    }
  },
  "verbose_text" : "Another significant achievement in the field of neurobiology and neurodevelopment is the wealth of knowledge that exists for Drosophila neurogenesis making it possible to analyze developing brains at the level of individual NB lineages.",
  "reading_complete" : "2020-08-04T14:38:07Z",
  "reader_type" : "machine",
  "reading_started" : "2020-08-04T14:37:42Z",
  "trigger" : "level",
  "evidence" : [ "level of individual NB" ],
  "pmc_id" : "7197723",
  "score" : 0
}