{
  "submitter" : "Reach",
  "model_relation" : "extension",
  "extracted_information" : {
    "interaction_type" : "transcribes",
    "negative_information" : false,
    "participant_b" : {
      "in_model" : true,
      "identifier" : "be:ROR",
      "entity_text" : "ROR",
      "entity_type" : "family"
    },
    "hypothesis_information" : false,
    "context" : {
      "Species" : [ "taxonomy:9606" ],
      "TissueType" : [ "uaz:CVCL_9S75" ]
    }
  },
  "verbose_text" : "Wang et al demonstrated that MLT downregulates the MLT nuclear receptor RZR / RAR related orphan receptor (ROR) gamma expression causing growth-inhibitory and anti-angiogenesis activity in human gastric cancer cells in vitro and in vivo.",
  "reading_complete" : "2020-08-03T14:40:48Z",
  "reader_type" : "machine",
  "reading_started" : "2020-08-03T14:39:42Z",
  "trigger" : "expression",
  "evidence" : [ "ROR)gamma expression" ],
  "pmc_id" : "6317691",
  "score" : 0
}