{
  "submitter" : "Reach",
  "model_relation" : "extension",
  "extracted_information" : {
    "interaction_type" : "transcribes",
    "negative_information" : false,
    "participant_b" : {
      "in_model" : true,
      "identifier" : "uaz:UAZ04370",
      "entity_text" : "circANKRD36",
      "entity_type" : "gene"
    },
    "hypothesis_information" : false,
    "context" : {
      "CellType" : [ "cl:CL:0000738" ],
      "Species" : [ "taxonomy:9606" ]
    }
  },
  "verbose_text" : "In conclusion, the present study demonstrated that circANKRD36 was expressed at high levels in leucocytes of patients with T2DM.",
  "reading_complete" : "2020-08-03T17:21:13Z",
  "reader_type" : "machine",
  "reading_started" : "2020-08-03T17:20:36Z",
  "trigger" : "expressed",
  "evidence" : [ "circANKRD36 was expressed" ],
  "pmc_id" : "6108858",
  "score" : 0
}