{
  "submitter" : "Reach",
  "model_relation" : "extension",
  "extracted_information" : {
    "interaction_type" : "transcribes",
    "negative_information" : false,
    "participant_b" : {
      "in_model" : true,
      "identifier" : "uaz:UAZ03219",
      "entity_text" : "SDF-1alpha",
      "entity_type" : "gene"
    },
    "hypothesis_information" : false,
    "context" : {
      "Species" : [ "taxonomy:9606" ],
      "TissueType" : [ "tissuelist:TS-0087" ],
      "Organ" : [ "uberon:UBERON:4300025" ],
      "CellType" : [ "cl:CL:0000034" ]
    }
  },
  "verbose_text" : "This is the first report of altered SDF-1alpha expression regulated by FGF-2 treatment in PDL cells derived from human permanent teeth.",
  "reading_complete" : "2020-08-02T13:27:54Z",
  "reader_type" : "machine",
  "reading_started" : "2020-08-02T13:27:25Z",
  "trigger" : "expression",
  "evidence" : [ "SDF-1alpha expression" ],
  "pmc_id" : "3577140",
  "score" : 0
}