{
  "submitter" : "Reach",
  "model_relation" : "extension",
  "extracted_information" : {
    "interaction_type" : "transcribes",
    "negative_information" : false,
    "participant_b" : {
      "in_model" : true,
      "identifier" : "uaz:UAZ01437",
      "entity_text" : "Arrestins 2 and 3",
      "entity_type" : "gene"
    },
    "hypothesis_information" : false,
    "context" : {
      "Species" : [ "taxonomy:10090" ]
    }
  },
  "verbose_text" : "Arrestins 2 and 3 (also referred to as beta-arrestin1 and beta-arrestin2) are ubiquitously expressed.",
  "reading_complete" : "2020-08-05T20:44:14Z",
  "reader_type" : "machine",
  "reading_started" : "2020-08-05T20:41:43Z",
  "trigger" : "expressed",
  "evidence" : [ "Arrestins 2 and 3 (also referred to as beta-arrestin1 and beta-arrestin2) are ubiquitously expressed" ],
  "pmc_id" : "3521152",
  "score" : 0
}