{
  "submitter" : "Reach",
  "model_relation" : "extension",
  "extracted_information" : {
    "interaction_type" : "increases_activity",
    "negative_information" : false,
    "participant_b" : {
      "in_model" : true,
      "identifier" : "mesh:D009362",
      "entity_text" : "metastasis",
      "entity_type" : "bioprocess"
    },
    "participant_a" : {
      "in_model" : true,
      "identifier" : "be:ERK",
      "entity_text" : "ERK",
      "entity_type" : "family"
    },
    "hypothesis_information" : false
  },
  "verbose_text" : "ERK activation causes cancer metastasis by inducing MMPs XREF_BIBR.",
  "reading_complete" : "2020-08-02T10:06:05Z",
  "reader_type" : "machine",
  "reading_started" : "2020-08-02T10:04:22Z",
  "trigger" : "causes",
  "evidence" : [ "ERK activation causes cancer metastasis" ],
  "pmc_id" : "6401504",
  "score" : 0
}