{
  "submitter" : "Reach",
  "model_relation" : "extension",
  "extracted_information" : {
    "interaction_type" : "transcribes",
    "negative_information" : false,
    "participant_b" : {
      "in_model" : true,
      "identifier" : "be:NFkappaB",
      "entity_text" : "NF-kappaB",
      "entity_type" : "gene"
    },
    "hypothesis_information" : false,
    "context" : {
      "TissueType" : [ "tissuelist:TS-0510" ],
      "Species" : [ "taxonomy:10116" ]
    }
  },
  "verbose_text" : "By administrating the brusatol, the inhibition of Nrf2 enhanced the expression of NF-kappaB, inhibits the antioxidant responses, and further reverse the protective effect of LBP on the LPS induced septic kidney injury.",
  "reading_complete" : "2020-08-05T19:52:41Z",
  "reader_type" : "machine",
  "reading_started" : "2020-08-05T19:51:40Z",
  "trigger" : "expression",
  "evidence" : [ "expression of NF-kappaB" ],
  "pmc_id" : "6585919",
  "score" : 0
}