{
  "submitter" : "Reach",
  "model_relation" : "extension",
  "extracted_information" : {
    "interaction_type" : "Amount",
    "negative_information" : false,
    "participant_b" : {
      "in_model" : true,
      "identifier" : "pfam:PF01342",
      "entity_text" : "sand",
      "entity_type" : "family"
    },
    "hypothesis_information" : false,
    "context" : {
      "Species" : [ "taxonomy:3847" ]
    }
  },
  "verbose_text" : "The locations had soils with relatively large amounts of silt and low amounts of sand and clay.",
  "reading_complete" : "2020-08-08T10:47:19Z",
  "reader_type" : "machine",
  "reading_started" : "2020-08-08T10:45:00Z",
  "trigger" : "amounts",
  "evidence" : [ "amounts of sand" ],
  "pmc_id" : "6167739",
  "score" : 0
}