{
  "submitter" : "Reach",
  "model_relation" : "extension",
  "extracted_information" : {
    "interaction_type" : "transcribes",
    "negative_information" : false,
    "participant_b" : {
      "in_model" : true,
      "identifier" : "uaz:UAZ02148",
      "entity_text" : "NF-kappaB1",
      "entity_type" : "gene"
    },
    "hypothesis_information" : false,
    "context" : {
      "Species" : [ "taxonomy:9606" ]
    }
  },
  "verbose_text" : "The compounds of roots 4beta,15-Dihydro-3-dehydrozaluzanin C and zaluzanin C were also tested for inhibitory activity of the expression of COX-2 and NF-kappaB1.",
  "reading_complete" : "2020-08-04T14:14:29Z",
  "reader_type" : "machine",
  "reading_started" : "2020-08-04T14:05:51Z",
  "trigger" : "expression",
  "evidence" : [ "expression of COX-2 and NF-kappaB1" ],
  "pmc_id" : "6410315",
  "score" : 0
}