{
  "submitter" : "Reach",
  "model_relation" : "extension",
  "extracted_information" : {
    "interaction_type" : "transcribes",
    "negative_information" : false,
    "participant_b" : {
      "in_model" : true,
      "identifier" : "uaz:UAZ17800",
      "entity_text" : "miR-200 family members",
      "entity_type" : "gene"
    },
    "hypothesis_information" : false,
    "context" : {
      "Species" : [ "taxonomy:9606" ],
      "CellType" : [ "cl:CL:0000034" ]
    }
  },
  "verbose_text" : "Because low expression of the miR-200 family members has been reported to promote the acquisition of stem cell properties and to induce EMT in tumor cells, we next determined the impact that PKCzeta regulation of miR-200s has on the mRNA expression levels of markers of stemness and EMT in shNT and shPKCzeta cells.",
  "reading_complete" : "2020-08-08T18:14:38Z",
  "reader_type" : "machine",
  "reading_started" : "2020-08-08T18:12:44Z",
  "trigger" : "expression",
  "evidence" : [ "expression of the miR-200 family members" ],
  "pmc_id" : "5958623",
  "score" : 0
}