{
  "submitter" : "Reach",
  "model_relation" : "extension",
  "extracted_information" : {
    "interaction_type" : "transcribes",
    "negative_information" : false,
    "participant_b" : {
      "in_model" : true,
      "identifier" : "uaz:UAZ02607",
      "entity_text" : "GsAPK",
      "entity_type" : "gene"
    },
    "hypothesis_information" : false,
    "context" : {
      "TissueType" : [ "tissuelist:TS-0883" ],
      "Species" : [ "taxonomy:4530" ]
    }
  },
  "verbose_text" : "We also demonstrated that over-expression of GsAPK in transgenic plants allowed better seed germination and root development than that in wild type under ABA stress (XREF_FIG) while the converse situation occurs in salinity stress.",
  "reading_complete" : "2020-08-08T12:41:55Z",
  "reader_type" : "machine",
  "reading_started" : "2020-08-08T12:40:38Z",
  "trigger" : "over-expression",
  "evidence" : [ "over-expression of GsAPK" ],
  "pmc_id" : "3306294",
  "score" : 0
}