{
  "submitter" : "Reach",
  "model_relation" : "extension",
  "extracted_information" : {
    "interaction_type" : "transcribes",
    "negative_information" : false,
    "participant_b" : {
      "in_model" : true,
      "identifier" : "uaz:UAZ03983",
      "entity_text" : "Trtesin transcripts",
      "entity_type" : "gene"
    },
    "hypothesis_information" : false,
    "context" : {
      "Species" : [ "taxonomy:9606" ]
    }
  },
  "verbose_text" : "The expression of Trtesin transcripts was> = 1000 fold higher in the mRNA library originating from PDB-grown fungi and demonstrating high antimicrobial activity.",
  "reading_complete" : "2020-08-04T17:20:48Z",
  "reader_type" : "machine",
  "reading_started" : "2020-08-04T17:14:37Z",
  "trigger" : "expression",
  "evidence" : [ "expression of Trtesin transcripts" ],
  "pmc_id" : "4199945",
  "score" : 0
}