{
  "submitter" : "Reach",
  "model_relation" : "extension",
  "extracted_information" : {
    "interaction_type" : "Amount",
    "negative_information" : false,
    "participant_b" : {
      "in_model" : true,
      "identifier" : "interpro:IPR000981",
      "entity_text" : "NH",
      "entity_type" : "family"
    },
    "hypothesis_information" : false
  },
  "verbose_text" : "However, with a larger amount of NH 3 adsorbed (0.27 mg g -1) and the higher maximum temperature of desorption (318 degreesC) in Sil20-Al, a larger number of acid sites are present, with a stronger acidity than in Sil80-Al (0.1 mg g -1, 286 degreesC).",
  "reading_complete" : "2020-08-03T14:15:06Z",
  "reader_type" : "machine",
  "reading_started" : "2020-08-03T14:13:06Z",
  "trigger" : "amount",
  "evidence" : [ "amount of NH" ],
  "pmc_id" : "4834610",
  "score" : 0
}