{
  "submitter" : "Reach",
  "model_relation" : "extension",
  "extracted_information" : {
    "interaction_type" : "transcribes",
    "negative_information" : false,
    "participant_b" : {
      "in_model" : true,
      "identifier" : "uaz:UAZ03108",
      "entity_text" : "PGC-1s increase gene",
      "entity_type" : "gene"
    },
    "hypothesis_information" : false,
    "context" : {
      "Species" : [ "taxonomy:10090" ],
      "TissueType" : [ "tissuelist:TS-0642" ]
    }
  },
  "verbose_text" : "Interestingly, it has previously been shown that PGC-1s increase gene expression of SOD2, GPX and enzymes responsible for glutathione biosynthesis, and both SOD2 and GPX have been implicated in cancer induced oxidative stress response.",
  "reading_complete" : "2020-08-03T15:12:14Z",
  "reader_type" : "machine",
  "reading_started" : "2020-08-03T15:10:30Z",
  "trigger" : "expression",
  "evidence" : [ "PGC-1s increase gene expression" ],
  "pmc_id" : "3712618",
  "score" : 0
}