{
  "submitter" : "Reach",
  "model_relation" : "extension",
  "extracted_information" : {
    "interaction_type" : "Amount",
    "negative_information" : false,
    "participant_b" : {
      "in_model" : true,
      "identifier" : "be:Troponin_C",
      "entity_text" : "troponin C",
      "entity_type" : "family"
    },
    "hypothesis_information" : false
  },
  "verbose_text" : "As shown in XREF_TABLE after feeding with TiO 2 NPs, the expression levels of troponin C and troponin C 25D were 10.98-fold and 2.93-fold, respectively, higher than those of the control group.",
  "reading_complete" : "2020-08-04T11:07:18Z",
  "reader_type" : "machine",
  "reading_started" : "2020-08-04T11:06:36Z",
  "trigger" : "levels",
  "evidence" : [ "levels of troponin C" ],
  "pmc_id" : "4920180",
  "score" : 0
}