{
  "submitter" : "Reach",
  "model_relation" : "extension",
  "extracted_information" : {
    "interaction_type" : "Amount",
    "negative_information" : false,
    "participant_b" : {
      "in_model" : true,
      "identifier" : "be:SOD",
      "entity_text" : "SOD",
      "entity_type" : "family"
    },
    "hypothesis_information" : false,
    "context" : {
      "TissueType" : [ "tissuelist:TS-0923" ],
      "Species" : [ "taxonomy:10116" ]
    }
  },
  "verbose_text" : "Levels of SOD activity in the latter group were significantly higher (p < 0.05) than those of the radiation-only animals at 30 days post-irradiation but similar at 15, 60 and 120 days post-irradiation (XREF_FIG).",
  "reading_complete" : "2020-08-03T16:06:00Z",
  "reader_type" : "machine",
  "reading_started" : "2020-08-03T16:04:37Z",
  "trigger" : "Levels",
  "evidence" : [ "Levels of SOD" ],
  "pmc_id" : "4072398",
  "score" : 0
}