{
  "submitter" : "Reach",
  "model_relation" : "extension",
  "extracted_information" : {
    "interaction_type" : "increases_activity",
    "negative_information" : false,
    "participant_b" : {
      "in_model" : true,
      "identifier" : "uaz:UAZ03199",
      "entity_text" : "RdRp inhibitors",
      "entity_type" : "simple_chemical"
    },
    "participant_a" : {
      "in_model" : true,
      "identifier" : "pfam:PF05183",
      "entity_text" : "RdRp",
      "entity_type" : "family"
    },
    "hypothesis_information" : false
  },
  "verbose_text" : "RdRp disrupting compounds : An attractive strategy for developing RdRp inhibitors appears to be interrupting the subunits interactions (the assembly course of the subunits in to a functional polymerase complex), and this strategy proves to be effective in recent studies.",
  "reading_complete" : "2020-08-03T12:50:27Z",
  "reader_type" : "machine",
  "reading_started" : "2020-08-03T12:47:36Z",
  "trigger" : "disrupting",
  "evidence" : [ "RdRp disrupting compounds: An attractive strategy for developing RdRp inhibitors" ],
  "pmc_id" : "5381247",
  "score" : 0
}