{
  "submitter" : "Reach",
  "model_relation" : "extension",
  "extracted_information" : {
    "interaction_type" : "transcribes",
    "negative_information" : false,
    "participant_b" : {
      "in_model" : true,
      "identifier" : "uaz:UAZ02146",
      "entity_text" : "miR-183-5p",
      "entity_type" : "gene"
    },
    "hypothesis_information" : false,
    "context" : {
      "CellLine" : [ "cellosaurus:CVCL_2529" ],
      "TissueType" : [ "tissuelist:TS-1222" ],
      "Organ" : [ "uberon:UBERON:0006611" ],
      "Species" : [ "taxonomy:9606" ]
    }
  },
  "verbose_text" : "Compared with normal adjacent tissues, the expression of miR-183-5p was decreased in endometrial cancer tissues, and the expression of Ezrin was significantly increased in endometrial cancer tissues.",
  "reading_complete" : "2020-08-02T14:14:31Z",
  "reader_type" : "machine",
  "reading_started" : "2020-08-02T14:13:19Z",
  "trigger" : "expression",
  "evidence" : [ "expression of miR-183-5p" ],
  "pmc_id" : "6192766",
  "score" : 0
}