{
  "submitter" : "Reach",
  "model_relation" : "extension",
  "extracted_information" : {
    "interaction_type" : "transcribes",
    "negative_information" : false,
    "participant_b" : {
      "in_model" : true,
      "identifier" : "uaz:UAZ04333",
      "entity_text" : "miR-20b",
      "entity_type" : "gene"
    },
    "hypothesis_information" : false,
    "context" : {
      "Species" : [ "taxonomy:10090" ],
      "TissueType" : [ "tissuelist:TS-1043" ],
      "CellType" : [ "cl:CL:2000008" ]
    }
  },
  "verbose_text" : "However, the exact mechanisms of miR-20b in the regulation of endothelial cell senescence remains to be further studied, for such a purpose, the present study successfully constructed HUVECs cells with high and low expression of miR-20b.",
  "reading_complete" : "2020-08-03T17:18:22Z",
  "reader_type" : "machine",
  "reading_started" : "2020-08-03T17:17:03Z",
  "trigger" : "expression",
  "evidence" : [ "expression of miR-20b" ],
  "pmc_id" : "7015131",
  "score" : 0
}