{
  "submitter" : "Reach",
  "model_relation" : "extension",
  "extracted_information" : {
    "interaction_type" : "decreases_activity",
    "negative_information" : false,
    "participant_b" : {
      "in_model" : true,
      "identifier" : "be:ERK",
      "entity_text" : "MAPK",
      "entity_type" : "family"
    },
    "participant_a" : {
      "in_model" : true,
      "identifier" : "pfam:PF15698",
      "entity_text" : "phosphatase",
      "entity_type" : "family"
    },
    "hypothesis_information" : false
  },
  "verbose_text" : "Other regulated genes include DUSP10, a phosphatase that blocks MAPK activation and can protect from oxidative stress, and PSMB9 a proteosomal component; suggesting a role for stress induced signalling in OA pathogenesis XREF_BIBR.",
  "reading_complete" : "2020-08-08T17:48:37Z",
  "reader_type" : "machine",
  "reading_started" : "2020-08-08T17:46:40Z",
  "trigger" : "blocks",
  "evidence" : [ "phosphatase that blocks MAPK" ],
  "pmc_id" : "3988961",
  "score" : 0
}