{
  "submitter" : "Reach",
  "model_relation" : "extension",
  "extracted_information" : {
    "interaction_type" : "transcribes",
    "negative_information" : false,
    "participant_b" : {
      "in_model" : true,
      "identifier" : "uaz:UAZ05314",
      "entity_text" : "PNL2",
      "entity_type" : "gene"
    },
    "hypothesis_information" : false,
    "context" : {
      "Species" : [ "taxonomy:9796" ],
      "TissueType" : [ "tissuelist:TS-0694" ],
      "CellType" : [ "cl:CL:0000148" ]
    }
  },
  "verbose_text" : "However, in the current case, no PNL2 expression was observed in any cells in the ciliary body or iris.",
  "reading_complete" : "2020-08-03T15:58:11Z",
  "reader_type" : "machine",
  "reading_started" : "2020-08-03T15:57:17Z",
  "trigger" : "expression",
  "evidence" : [ "PNL2 expression" ],
  "pmc_id" : "5676260",
  "score" : 0
}