{
  "submitter" : "Reach",
  "model_relation" : "extension",
  "extracted_information" : {
    "interaction_type" : "Amount",
    "negative_information" : false,
    "participant_b" : {
      "in_model" : true,
      "identifier" : "pfam:PF00210",
      "entity_text" : "ferritin",
      "entity_type" : "family"
    },
    "hypothesis_information" : false,
    "context" : {
      "Organ" : [ "uberon:UBERON:0006611" ],
      "Species" : [ "taxonomy:9606" ]
    }
  },
  "verbose_text" : "XREF_BIBR Other frequent findings, which have been linked to poor prognosis, are elevated levels of D-dimer, interleukin 6, lactate dehydrogenase, and ferritin.",
  "reading_complete" : "2020-07-28T11:46:18Z",
  "reader_type" : "machine",
  "reading_started" : "2020-07-28T11:44:46Z",
  "trigger" : "levels",
  "evidence" : [ "levels of D-dimer, interleukin 6, lactate dehydrogenase, and ferritin" ],
  "pmc_id" : "7205723",
  "score" : 0
}