{
  "submitter" : "Reach",
  "model_relation" : "extension",
  "extracted_information" : {
    "interaction_type" : "adds_modification",
    "modifications" : [ {
      "modification_type" : "phosphorylation"
    } ],
    "negative_information" : false,
    "participant_b" : {
      "in_model" : true,
      "identifier" : "be:AKT",
      "entity_text" : "Akt",
      "entity_type" : "family"
    },
    "is_direct" : false,
    "hypothesis_information" : false,
    "context" : {
      "Species" : [ "taxonomy:10090" ]
    }
  },
  "verbose_text" : "In Nprl2 KO mESCs, upregulated S6K seemingly causes conventional negative feedback and attenuates Akt and consequently Gsk3 phosphorylation.",
  "reading_complete" : "2020-08-08T14:02:02Z",
  "reader_type" : "machine",
  "reading_started" : "2020-08-08T13:59:32Z",
  "trigger" : "phosphorylation",
  "evidence" : [ "Akt and consequently Gsk3 phosphorylation" ],
  "pmc_id" : "6057492",
  "score" : 0
}