{
  "submitter" : "Reach",
  "model_relation" : "extension",
  "extracted_information" : {
    "interaction_type" : "transcribes",
    "negative_information" : false,
    "participant_b" : {
      "in_model" : true,
      "identifier" : "uaz:UAZ00383",
      "entity_text" : "CeJAM3",
      "entity_type" : "gene"
    },
    "hypothesis_information" : false,
    "context" : {
      "Species" : [ "taxonomy:76720" ]
    }
  },
  "verbose_text" : "CeJAZ1 expression was induced 2 HAW, while minor increase in CeJAM3 and CeCOI1 expression was noted 2/4 HAW and 48 HAW, respectively, according to the qPCR results (XREF_FIG).",
  "reading_complete" : "2020-08-04T11:27:13Z",
  "reader_type" : "machine",
  "reading_started" : "2020-08-04T11:13:54Z",
  "trigger" : "expression",
  "evidence" : [ "CeJAM3 and CeCOI1 expression" ],
  "pmc_id" : "6963686",
  "score" : 0
}