{
  "submitter" : "Reach",
  "model_relation" : "extension",
  "extracted_information" : {
    "interaction_type" : "transcribes",
    "negative_information" : false,
    "participant_b" : {
      "in_model" : true,
      "identifier" : "uaz:UAZ01236",
      "entity_text" : "NtMLO1",
      "entity_type" : "gene"
    },
    "hypothesis_information" : false,
    "context" : {
      "CellLine" : [ "cellosaurus:CVCL_7904" ],
      "Species" : [ "taxonomy:4097" ]
    }
  },
  "verbose_text" : "We hypothesised that overexpression of NtMLO1 would have restored PM susceptibility in the tomato Slmlo1 mutant line, thereby demonstrating functional conservation between NtMLO1 and SlMLO1.",
  "reading_complete" : "2020-07-28T16:30:12Z",
  "reader_type" : "machine",
  "reading_started" : "2020-07-28T16:28:44Z",
  "trigger" : "overexpression",
  "evidence" : [ "overexpression of NtMLO1" ],
  "pmc_id" : "4569668",
  "score" : 0
}