{
  "submitter" : "Reach",
  "model_relation" : "extension",
  "extracted_information" : {
    "interaction_type" : "transcribes",
    "negative_information" : false,
    "participant_b" : {
      "in_model" : true,
      "identifier" : "be:PKA",
      "entity_text" : "PKA",
      "entity_type" : "gene"
    },
    "hypothesis_information" : false,
    "context" : {
      "Species" : [ "taxonomy:9606" ],
      "TissueType" : [ "tissuelist:TS-0895" ]
    }
  },
  "verbose_text" : "Examining the RTOG 92-02 biorepository for PKA overexpression resulted in IHC analysis on 161 patients from the STAD + RT control arm and 152 patient samples from the LTAD + RT arm (313 total cases) [XREF_BIBR].",
  "reading_complete" : "2020-07-28T14:17:49Z",
  "reader_type" : "machine",
  "reading_started" : "2020-07-28T14:04:53Z",
  "trigger" : "overexpression",
  "evidence" : [ "PKA overexpression" ],
  "pmc_id" : "3412203",
  "score" : 0
}