{
  "submitter" : "Reach",
  "model_relation" : "extension",
  "extracted_information" : {
    "interaction_type" : "transcribes",
    "negative_information" : false,
    "participant_b" : {
      "in_model" : true,
      "identifier" : "uaz:UAZ03708",
      "entity_text" : "NOTCH2NLC",
      "entity_type" : "gene"
    },
    "hypothesis_information" : false,
    "context" : {
      "Species" : [ "taxonomy:9606" ],
      "TissueType" : [ "tissuelist:TS-0079" ]
    }
  },
  "verbose_text" : "Furthermore, we determined the expression of NOTCH2NLC in the blood of both NIID affected case subjects and control subjects, and did not detect significant changes in expression for the NIID affected case subjects with expanded GGC repeats (XREF_FIG B), indicating that the expanded GGC repeat does not alter the expression of NOTCH2NLC and that the GGC repeat RNA could potentially play a role in the molecular pathogenesis of NIID.",
  "reading_complete" : "2020-08-08T13:46:11Z",
  "reader_type" : "machine",
  "reading_started" : "2020-08-08T13:42:46Z",
  "trigger" : "expression",
  "evidence" : [ "expression of NOTCH2NLC" ],
  "pmc_id" : "6612530",
  "score" : 0
}