{
  "submitter" : "Reach",
  "model_relation" : "extension",
  "extracted_information" : {
    "interaction_type" : "transcribes",
    "negative_information" : false,
    "participant_b" : {
      "in_model" : true,
      "identifier" : "uaz:UAZ03601",
      "entity_text" : "miR-367-3p",
      "entity_type" : "gene"
    },
    "hypothesis_information" : false,
    "context" : {
      "CellLine" : [ "cellosaurus:CVCL_0022" ],
      "Species" : [ "taxonomy:10090" ]
    }
  },
  "verbose_text" : "Knockdown of OIP5-AS1 combined with over-expression of PIWIL3 and miR-367-3p restrained tumor growth and prolonged nude mice survival.",
  "reading_complete" : "2020-08-03T13:21:03Z",
  "reader_type" : "machine",
  "reading_started" : "2020-08-03T13:16:29Z",
  "trigger" : "over-expression",
  "evidence" : [ "over-expression of PIWIL3 and miR-367-3p" ],
  "pmc_id" : "5817112",
  "score" : 0
}