{
  "submitter" : "Reach",
  "model_relation" : "extension",
  "extracted_information" : {
    "interaction_type" : "transcribes",
    "negative_information" : false,
    "participant_b" : {
      "in_model" : true,
      "identifier" : "uaz:UAZ00083",
      "entity_text" : "Ki-67",
      "entity_type" : "gene"
    },
    "hypothesis_information" : false,
    "context" : {
      "Species" : [ "taxonomy:9606" ],
      "TissueType" : [ "tissuelist:TS-0564" ]
    }
  },
  "verbose_text" : "In 2006, Wang et al., who evaluated the expression of leptin and its receptor in HCC specimens by immunostaining, further correlated the expression profile with Ki-67 expression, intratumor MVD, and overall survival and provided clinical evidence on the prognostic roles of leptin and OBR in HCC patients [XREF_BIBR, XREF_BIBR].",
  "reading_complete" : "2020-08-08T16:54:25Z",
  "reader_type" : "machine",
  "reading_started" : "2020-08-08T16:47:15Z",
  "trigger" : "expression",
  "evidence" : [ "Ki-67 expression" ],
  "pmc_id" : "3179873",
  "score" : 0
}