{
  "submitter" : "Reach",
  "model_relation" : "extension",
  "extracted_information" : {
    "interaction_type" : "transcribes",
    "negative_information" : false,
    "participant_b" : {
      "in_model" : true,
      "identifier" : "uaz:UAZ01456",
      "entity_text" : "HBx-LINE-1",
      "entity_type" : "gene"
    },
    "hypothesis_information" : false,
    "context" : {
      "Species" : [ "taxonomy:9606" ],
      "TissueType" : [ "tissuelist:TS-0455" ]
    }
  },
  "verbose_text" : "Intriguingly, HBx-LINE-1 expression results in formation of a long noncoding RNA (lncRNA), which interacts with and induces the nuclear translocation of beta-catenin.",
  "reading_complete" : "2020-07-28T13:46:47Z",
  "reader_type" : "machine",
  "reading_started" : "2020-07-28T13:35:16Z",
  "trigger" : "expression",
  "evidence" : [ "HBx-LINE-1 expression" ],
  "pmc_id" : "5384359",
  "score" : 0
}