{
  "submitter" : "Reach",
  "model_relation" : "extension",
  "extracted_information" : {
    "interaction_type" : "transcribes",
    "negative_information" : false,
    "participant_b" : {
      "in_model" : true,
      "identifier" : "uaz:UAZ01830",
      "entity_text" : "MtDEF4.2",
      "entity_type" : "gene"
    },
    "hypothesis_information" : false,
    "context" : {
      "CellLine" : [ "cellosaurus:CVCL_0372" ],
      "Species" : [ "taxonomy:4565" ],
      "TissueType" : [ "tissuelist:TS-0210" ]
    }
  },
  "verbose_text" : "To obtain a high level expression of MtDEF4.2 in transgenic wheat, a 231 bp full-length MtDef4.2 cDNA sequence was synthesized (GenScript Inc., NJ) using the monocot preferred codons and cloned as a NcoI-XbaI fragment between the Tobacco etch virus (TEV) mRNA leader sequence and Cauliflower mosaic virus (CaMV) 35S polyadenylation signal in the pRTL2 vector.",
  "reading_complete" : "2020-07-28T17:09:10Z",
  "reader_type" : "machine",
  "reading_started" : "2020-07-28T17:06:24Z",
  "trigger" : "expression",
  "evidence" : [ "expression of MtDEF4.2" ],
  "pmc_id" : "5243879",
  "score" : 0
}