{
  "submitter" : "Reach",
  "model_relation" : "extension",
  "extracted_information" : {
    "interaction_type" : "adds_modification",
    "modifications" : [ {
      "modification_type" : "hydrolysis"
    } ],
    "negative_information" : false,
    "participant_b" : {
      "in_model" : true,
      "identifier" : "interpro:IPR001461",
      "entity_text" : "pepsin",
      "entity_type" : "family"
    },
    "is_direct" : false,
    "hypothesis_information" : false,
    "context" : {
      "CellLine" : [ "cellosaurus:CVCL_E626" ],
      "Species" : [ "taxonomy:10116" ]
    }
  },
  "verbose_text" : "The myocardial hydroxyproline (Hyp) concentration was determined by pepsin acid hydrolysis.",
  "reading_complete" : "2020-08-04T19:24:11Z",
  "reader_type" : "machine",
  "reading_started" : "2020-08-04T19:22:38Z",
  "trigger" : "hydrolysis",
  "evidence" : [ "pepsin acid hydrolysis" ],
  "pmc_id" : "5877828",
  "score" : 0
}