{
  "submitter" : "Reach",
  "model_relation" : "extension",
  "extracted_information" : {
    "interaction_type" : "transcribes",
    "negative_information" : false,
    "participant_b" : {
      "in_model" : true,
      "identifier" : "pfam:PF01103",
      "entity_text" : "surface antigen",
      "entity_type" : "family"
    },
    "hypothesis_information" : false,
    "context" : {
      "Species" : [ "taxonomy:10407" ]
    }
  },
  "verbose_text" : "The inhibition of GFAT1 leads to a significant reduction in the expression of hepatitis B surface antigen (HBsAg) (XREF_FIG).",
  "reading_complete" : "2020-08-04T10:15:16Z",
  "reader_type" : "machine",
  "reading_started" : "2020-08-04T10:14:16Z",
  "trigger" : "expression",
  "evidence" : [ "expression of hepatitis B surface antigen" ],
  "pmc_id" : "4325332",
  "score" : 0
}