{
  "submitter" : "Reach",
  "model_relation" : "extension",
  "extracted_information" : {
    "interaction_type" : "Amount",
    "negative_information" : false,
    "participant_b" : {
      "in_model" : true,
      "identifier" : "pfam:PF00191",
      "entity_text" : "Annexin",
      "entity_type" : "family"
    },
    "hypothesis_information" : false,
    "context" : {
      "Species" : [ "taxonomy:10116" ]
    }
  },
  "verbose_text" : "Treatment with OGD increased the amount of activated caspase-3 and Annexin V-PE/7-AAD-positive cells in H9C2 cells.",
  "reading_complete" : "2020-08-03T09:37:20Z",
  "reader_type" : "machine",
  "reading_started" : "2020-08-03T09:35:45Z",
  "trigger" : "amount",
  "evidence" : [ "amount of activated caspase-3 and Annexin" ],
  "pmc_id" : "5196885",
  "score" : 0
}