{
  "submitter" : "Reach",
  "model_relation" : "extension",
  "extracted_information" : {
    "interaction_type" : "transcribes",
    "negative_information" : false,
    "participant_b" : {
      "in_model" : true,
      "identifier" : "pfam:PF01353",
      "entity_text" : "GFP",
      "entity_type" : "family"
    },
    "hypothesis_information" : false,
    "context" : {
      "TissueType" : [ "tissuelist:TS-0273" ],
      "Organ" : [ "uberon:UBERON:0003257" ],
      "Species" : [ "taxonomy:10090" ]
    }
  },
  "verbose_text" : "In addition, GFP was expressed in the septum transversum at E8.5, but was absent in the adjacent foregut endoderm at E9.5 (XREF_FIG Ab).",
  "reading_complete" : "2020-08-04T10:13:56Z",
  "reader_type" : "machine",
  "reading_started" : "2020-08-04T10:12:41Z",
  "trigger" : "expressed",
  "evidence" : [ "GFP was expressed" ],
  "pmc_id" : "6310872",
  "score" : 0
}