{
  "submitter" : "Reach",
  "model_relation" : "extension",
  "extracted_information" : {
    "interaction_type" : "transcribes",
    "negative_information" : false,
    "participant_b" : {
      "in_model" : true,
      "identifier" : "uaz:UAZ03976",
      "entity_text" : "EYFP",
      "entity_type" : "gene"
    },
    "hypothesis_information" : false,
    "context" : {
      "CellLine" : [ "cellosaurus:CVCL_1061" ],
      "Organ" : [ "uberon:UBERON:0004529" ],
      "CellType" : [ "cl:CL:0000540" ],
      "Species" : [ "taxonomy:10116" ]
    }
  },
  "verbose_text" : "The immunohistochemical visualization of CGRP expressing cells in the EYFP expressing slices suggested that a subset of CGRP positive neurons in and around the LPB would be a part of the neurons projecting to the CeC.",
  "reading_complete" : "2020-08-08T16:44:52Z",
  "reader_type" : "machine",
  "reading_started" : "2020-08-08T16:38:02Z",
  "trigger" : "expressing",
  "evidence" : [ "EYFP-expressing" ],
  "pmc_id" : "4922599",
  "score" : 0
}