{
  "submitter" : "Reach",
  "model_relation" : "extension",
  "extracted_information" : {
    "interaction_type" : "transcribes",
    "negative_information" : false,
    "participant_b" : {
      "in_model" : true,
      "identifier" : "uaz:UAZ01190",
      "entity_text" : "class II antigens",
      "entity_type" : "gene"
    },
    "hypothesis_information" : false,
    "context" : {
      "TissueType" : [ "tissuelist:TS-0095" ],
      "CellType" : [ "cl:CL:0000127" ],
      "Species" : [ "taxonomy:10116" ]
    }
  },
  "verbose_text" : "Astrocytes can function as antigen presenting cells (APC) upon expression of class II antigens, which are induced by interferon-gamma (IFN-gamma).",
  "reading_complete" : "2020-07-28T14:55:02Z",
  "reader_type" : "machine",
  "reading_started" : "2020-07-28T14:54:57Z",
  "trigger" : "expression",
  "evidence" : [ "expression of class II antigens" ],
  "pmc_id" : "7119699",
  "score" : 0
}