{
  "submitter" : "Reach",
  "model_relation" : "extension",
  "extracted_information" : {
    "interaction_type" : "increases_activity",
    "negative_information" : false,
    "participant_b" : {
      "in_model" : true,
      "identifier" : "pfam:PF02985",
      "entity_text" : "heat",
      "entity_type" : "family"
    },
    "participant_a" : {
      "in_model" : true,
      "identifier" : "pfam:PF00823",
      "entity_text" : "PPE",
      "entity_type" : "family"
    },
    "hypothesis_information" : false
  },
  "verbose_text" : "These findings are confirmed by the fact that the heat strain caused by PPE is a result of excess body heat storage which can be attributed to the combined effect of PPE characteristics, environmental conditions, and the level of physical activity.",
  "reading_complete" : "2020-08-08T08:52:57Z",
  "reader_type" : "machine",
  "reading_started" : "2020-08-08T08:51:09Z",
  "trigger" : "caused",
  "evidence" : [ "heat strain caused by PPE" ],
  "pmc_id" : "7301811",
  "score" : 0
}