{
  "submitter" : "Reach",
  "model_relation" : "extension",
  "extracted_information" : {
    "interaction_type" : "transcribes",
    "negative_information" : false,
    "participant_b" : {
      "in_model" : true,
      "identifier" : "pfam:PF16489",
      "entity_text" : "gain",
      "entity_type" : "family"
    },
    "hypothesis_information" : false
  },
  "verbose_text" : "Although on a single movement only one feedback gain was actually expressed (because of our applied perturbation), the feedback gains for the left and right visuomotor responses had to be appropriately set, as the direction of the perturbation was not known in advance (experiment 2).",
  "reading_complete" : "2020-08-08T11:51:34Z",
  "reader_type" : "machine",
  "reading_started" : "2020-08-08T11:49:11Z",
  "trigger" : "expressed",
  "evidence" : [ "gain was actually expressed" ],
  "pmc_id" : "4274920",
  "score" : 0
}