{
  "submitter" : "Reach",
  "model_relation" : "extension",
  "extracted_information" : {
    "interaction_type" : "adds_modification",
    "modifications" : [ {
      "modification_type" : "phosphorylation"
    } ],
    "negative_information" : false,
    "participant_b" : {
      "in_model" : true,
      "identifier" : "be:p38",
      "entity_text" : "p38 MAPK",
      "entity_type" : "family"
    },
    "is_direct" : false,
    "hypothesis_information" : false,
    "context" : {
      "CellLine" : [ "cellosaurus:CVCL_0455" ],
      "Species" : [ "taxonomy:9606" ]
    }
  },
  "verbose_text" : "Western blot was performed for analysis of phosphorylation of ERK1/2 and p38 MAPK.",
  "reading_complete" : "2020-08-03T19:07:02Z",
  "reader_type" : "machine",
  "reading_started" : "2020-08-03T19:04:23Z",
  "trigger" : "phosphorylation",
  "evidence" : [ "phosphorylation of ERK1/2 and p38 MAPK" ],
  "pmc_id" : "4135156",
  "score" : 0
}