{
  "submitter" : "Reach",
  "model_relation" : "extension",
  "extracted_information" : {
    "interaction_type" : "Amount",
    "negative_information" : false,
    "participant_b" : {
      "in_model" : true,
      "identifier" : "interpro:IPR000796",
      "entity_text" : "transaminase",
      "entity_type" : "family"
    },
    "hypothesis_information" : false,
    "context" : {
      "CellLine" : [ "cellosaurus:CVCL_Y548" ],
      "TissueType" : [ "tissuelist:TS-0923" ],
      "Species" : [ "taxonomy:9606" ]
    }
  },
  "verbose_text" : "The higher concentration of respirable suspended particulate matter and nitrogen dioxide in air was associated with increase in alanine transaminase level (p < 0.0001) by 0.8 times (95% CI 0.589-1.049) and by 2.8 times (95% CI 2.067-3.681) respectively in the exposed group.",
  "reading_complete" : "2020-08-08T15:20:51Z",
  "reader_type" : "machine",
  "reading_started" : "2020-08-08T15:19:00Z",
  "trigger" : "level",
  "evidence" : [ "transaminase level" ],
  "pmc_id" : "4395329",
  "score" : 0
}