{
  "submitter" : "Reach",
  "model_relation" : "extension",
  "extracted_information" : {
    "interaction_type" : "decreases_activity",
    "negative_information" : true,
    "participant_b" : {
      "in_model" : true,
      "identifier" : "be:TGFB",
      "entity_text" : "TGFbeta",
      "entity_type" : "family"
    },
    "participant_a" : {
      "in_model" : true,
      "identifier" : "interpro:IPR003939",
      "entity_text" : "TGFbeta1",
      "entity_type" : "family"
    },
    "hypothesis_information" : true
  },
  "verbose_text" : "Fig. XREF_FIG E shows that TGFbeta1 repressed the promoter activity of wild-type but not the mutant reporter, suggesting that lncRNA-LET is a downstream target of the canonical TGFbeta signaling pathway.",
  "reading_complete" : "2020-08-03T14:36:26Z",
  "reader_type" : "machine",
  "reading_started" : "2020-08-03T14:34:54Z",
  "trigger" : "repressed",
  "evidence" : [ "TGFbeta1 repressed the promoter activity of wild-type but not the mutant reporter, suggesting that lncRNA-LET is a downstream target of the canonical TGFbeta" ],
  "pmc_id" : "5566105",
  "score" : 0
}