{
  "submitter" : "Reach",
  "model_relation" : "extension",
  "extracted_information" : {
    "interaction_type" : "transcribes",
    "negative_information" : false,
    "participant_b" : {
      "in_model" : true,
      "identifier" : "pfam:PF00210",
      "entity_text" : "ferritin",
      "entity_type" : "family"
    },
    "hypothesis_information" : false,
    "context" : {
      "Species" : [ "taxonomy:10090" ],
      "TissueType" : [ "tissuelist:TS-0416" ]
    }
  },
  "verbose_text" : "It was shown that the induced expression of ferritin caused significant T2 relaxation time shortening XREF_BIBR.",
  "reading_complete" : "2020-08-02T11:50:50Z",
  "reader_type" : "machine",
  "reading_started" : "2020-08-02T11:49:49Z",
  "trigger" : "expression",
  "evidence" : [ "expression of ferritin" ],
  "pmc_id" : "3337732",
  "score" : 0
}