{
  "submitter" : "Reach",
  "model_relation" : "extension",
  "extracted_information" : {
    "interaction_type" : "Amount",
    "negative_information" : false,
    "participant_b" : {
      "in_model" : true,
      "identifier" : "pfam:PF02246",
      "entity_text" : "B1",
      "entity_type" : "family"
    },
    "hypothesis_information" : false,
    "context" : {
      "TissueType" : [ "tissuelist:TS-0160" ],
      "Species" : [ "taxonomy:9606" ]
    }
  },
  "verbose_text" : "An increase in the levels of cyclin B1 and A regulates Cdk2 kinase expression at the G2-M phase.",
  "reading_complete" : "2020-08-02T16:28:40Z",
  "reader_type" : "machine",
  "reading_started" : "2020-08-02T16:27:51Z",
  "trigger" : "levels",
  "evidence" : [ "levels of cyclin B1" ],
  "pmc_id" : "3776715",
  "score" : 0
}